Metadata-Version: 2.1
Name: easy-model-repo
Version: 0.0.6
Summary: sdk help users to use model repo
Home-page: https://gitlab.stonewise.cn/mlsys/easy-model.git
Author: SoutherLea
Author-email: lizhengnan@stonewise.cn
Classifier: Programming Language :: Python :: 3
Classifier: License :: OSI Approved :: MIT License
Classifier: Operating System :: OS Independent
Requires-Python: >=3.5
